README.md
setup.py
bin/kms-decrypt
bin/kms-encrypt
chalice_helpers/__init__.py
chalice_helpers.egg-info/PKG-INFO
chalice_helpers.egg-info/SOURCES.txt
chalice_helpers.egg-info/dependency_links.txt
chalice_helpers.egg-info/not-zip-safe
chalice_helpers.egg-info/requires.txt
chalice_helpers.egg-info/top_level.txt