Metadata-Version: 1.0
Name: chalice-helpers
Version: 0.1
Summary: Some utilities for AWS Chalice
Home-page: http://github.com/stechstudio/chalice_helpers
Author: Bubba Hines
Author-email: bubba@stechstudio.com
License: MIT
Platform: UNKNOWN
